{
    "column_width": {}, 
    "table_data": {
        "data": [
            [
                "Key", 
                "Type", 
                "Value", 
                "Des"
            ], 
            [
                "RevivalPointX", 
                "float", 
                "0", 
                ""
            ], 
            [
                "RevivalPointY", 
                "float", 
                "0", 
                null
            ], 
            [
                "IsFirstTalk", 
                "bool", 
                "true", 
                "\u662f\u5426\u4e3a\u7b2c\u4e00\u6b21\u5bf9\u8bdd"
            ], 
            [
                null, 
                null, 
                null, 
                null
            ], 
            [
                null, 
                null, 
                null, 
                null
            ], 
            [
                null, 
                null, 
                null, 
                null
            ], 
            [
                null, 
                null, 
                null, 
                null
            ], 
            [
                null, 
                null, 
                null, 
                null
            ], 
            [
                null, 
                null, 
                null, 
                null
            ], 
            [
                null, 
                null, 
                null, 
                null
            ], 
            [
                null, 
                null, 
                null, 
                null
            ], 
            [
                null, 
                null, 
                null, 
                null
            ], 
            [
                null, 
                null, 
                null, 
                null
            ], 
            [
                null, 
                null, 
                null, 
                null
            ], 
            [
                null, 
                null, 
                null, 
                null
            ], 
            [
                null, 
                null, 
                null, 
                null
            ], 
            [
                null, 
                null, 
                null, 
                null
            ], 
            [
                null, 
                null, 
                null, 
                null
            ], 
            [
                null, 
                null, 
                null, 
                null
            ], 
            [
                null, 
                null, 
                null, 
                null
            ], 
            [
                null, 
                null, 
                null, 
                null
            ], 
            [
                null, 
                null, 
                null, 
                null
            ], 
            [
                null, 
                null, 
                null, 
                null
            ], 
            [
                null, 
                null, 
                null, 
                null
            ], 
            [
                null, 
                null, 
                null, 
                null
            ], 
            [
                null, 
                null, 
                null, 
                null
            ], 
            [
                null, 
                null, 
                null, 
                null
            ], 
            [
                null, 
                null, 
                null, 
                null
            ], 
            [
                null, 
                null, 
                null, 
                null
            ]
        ], 
        "key": [
            0
        ], 
        "kv_key_type": "str"
    }, 
    "table_type": 1, 
    "tid": "0cea5eb4-7565-4a74-837d-3a7bc1c26e86"
}